<annotation>
	<folder></folder>
	<filename>I8_JPG.rf.fb9bb0a6a32d5b0fba0ab634fdf940a6.jpg</filename>
	<path>I8_JPG.rf.fb9bb0a6a32d5b0fba0ab634fdf940a6.jpg</path>
	<source>
		<database>roboflow.ai</database>
	</source>
	<size>
		<width>1024</width>
		<height>1024</height>
		<depth>3</depth>
	</size>
	<segmented>0</segmented>
	<object>
		<name>I</name>
		<pose>Unspecified</pose>
		<truncated>0</truncated>
		<difficult>0</difficult>
		<occluded>0</occluded>
		<bndbox>
			<xmin>365</xmin>
			<xmax>504</xmax>
			<ymin>567</ymin>
			<ymax>691</ymax>
		</bndbox>
	</object>
</annotation>
